javanese_stemmer/__init__.py
javanese_stemmer/stemmer.py
javanese_stemmer-1.0.0.dist-info/licenses/LICENSE
javanese_stemmer-1.0.0.dist-info/METADATA
javanese_stemmer-1.0.0.dist-info/WHEEL
javanese_stemmer-1.0.0.dist-info/top_level.txt
javanese_stemmer-1.0.0.dist-info/RECORD
